LICENSE
MANIFEST.in
README.md
setup.py
django_fernet_fieldhasher.egg-info/PKG-INFO
django_fernet_fieldhasher.egg-info/SOURCES.txt
django_fernet_fieldhasher.egg-info/dependency_links.txt
django_fernet_fieldhasher.egg-info/requires.txt
django_fernet_fieldhasher.egg-info/top_level.txt
fernet_fieldhasher/__init__.py
fernet_fieldhasher/fields.py
fernet_fieldhasher/hashers.py
fernet_fieldhasher/forms/__init__.py
fernet_fieldhasher/forms/fields.py
fernet_fieldhasher/forms/widgets.py
fernet_fieldhasher/templates/fernet_fieldhasher/forms/read_only_password_hash.html