Metadata-Version: 2.1
Name: django-fernet-fieldhasher
Version: 1.5.0
Summary: Creating encrypted database fields with the algorithm with cryptography.fernet
Home-page: https://github.com/alexsilva/django-fernet-fieldhasher
Author: alex
Author-email: 
License: MIT
License-File: LICENSE
